rotalabs_steer/__init__.py
rotalabs_steer/_version.py
rotalabs_steer/utils.py
rotalabs_steer/core/__init__.py
rotalabs_steer/core/configs.py
rotalabs_steer/core/hooks.py
rotalabs_steer/core/injection.py
rotalabs_steer/core/vectors.py
rotalabs_steer/datasets/__init__.py
rotalabs_steer/datasets/assertiveness_pairs.py
rotalabs_steer/datasets/base.py
rotalabs_steer/datasets/conciseness_pairs.py
rotalabs_steer/datasets/creativity_pairs.py
rotalabs_steer/datasets/empathy_pairs.py
rotalabs_steer/datasets/formality_pairs.py
rotalabs_steer/datasets/hierarchy_pairs.py
rotalabs_steer/datasets/humor_pairs.py
rotalabs_steer/datasets/refusal_pairs.py
rotalabs_steer/datasets/technical_depth_pairs.py
rotalabs_steer/datasets/tool_pairs.py
rotalabs_steer/datasets/uncertainty_pairs.py
rotalabs_steer/evaluation/__init__.py
rotalabs_steer/evaluation/analysis.py
rotalabs_steer/evaluation/llm_judge.py
rotalabs_steer/evaluation/metrics.py
rotalabs_steer/extraction/__init__.py
rotalabs_steer/extraction/base.py
rotalabs_steer/extraction/caa.py
rotalabs_steer/integrations/__init__.py
rotalabs_steer/integrations/langchain/__init__.py
rotalabs_steer/integrations/langchain/steered_agent.py
rotalabs_steer/integrations/langchain/steered_chat.py
rotalabs_steer/integrations/langchain/steered_llm.py
rotalabs_steer-1.0.0.dist-info/METADATA
rotalabs_steer-1.0.0.dist-info/WHEEL
rotalabs_steer-1.0.0.dist-info/licenses/LICENSE
rotalabs_steer-1.0.0.dist-info/RECORD
