Metadata-Version: 2.4
Name: rotalabs-steer
Version: 1.0.0
Summary: Control agent behaviors through activation steering - Apply steering vectors to LLMs at inference time without retraining
Project-URL: Homepage, https://rotalabs.ai
Project-URL: Repository, https://github.com/rotalabs/rotalabs-steer
Project-URL: Documentation, https://rotalabs.github.io/rotalabs-steer/
Author-email: Subhadip Mitra <subhadip@rotalabs.ai>, Rotalabs Research <research@rotalabs.ai>
License-Expression: AGPL-3.0-or-later
License-File: LICENSE
Keywords: agents,ai-safety,behavior-control,interpretability,llm,representation-engineering,steering-vectors
Classifier: Development Status :: 4 - Beta
Classifier: Intended Audience :: Developers
Classifier: Intended Audience :: Science/Research
Classifier: License :: OSI Approved :: GNU Affero General Public License v3 or later (AGPLv3+)
Classifier: Programming Language :: Python :: 3
Classifier: Programming Language :: Python :: 3.9
Classifier: Programming Language :: Python :: 3.10
Classifier: Programming Language :: Python :: 3.11
Classifier: Programming Language :: Python :: 3.12
Classifier: Topic :: Scientific/Engineering :: Artificial Intelligence
Requires-Python: >=3.9
Requires-Dist: accelerate>=0.25.0
Requires-Dist: einops>=0.7.0
Requires-Dist: numpy>=1.24.0
Requires-Dist: pandas>=2.0.0
Requires-Dist: pyyaml>=6.0
Requires-Dist: safetensors>=0.4.0
Requires-Dist: scikit-learn>=1.3.0
Requires-Dist: scipy>=1.10.0
Requires-Dist: torch>=2.0.0
Requires-Dist: tqdm>=4.65.0
Requires-Dist: transformers>=4.35.0
Provides-Extra: all
Requires-Dist: anthropic>=0.18.0; extra == 'all'
Requires-Dist: langchain-community>=0.0.20; extra == 'all'
Requires-Dist: langchain-core>=0.1.0; extra == 'all'
Requires-Dist: langchain>=0.1.0; extra == 'all'
Requires-Dist: matplotlib>=3.7.0; extra == 'all'
Requires-Dist: plotly>=5.15.0; extra == 'all'
Requires-Dist: seaborn>=0.12.0; extra == 'all'
Provides-Extra: dev
Requires-Dist: black>=23.0.0; extra == 'dev'
Requires-Dist: mypy>=1.5.0; extra == 'dev'
Requires-Dist: pytest-cov>=4.1.0; extra == 'dev'
Requires-Dist: pytest>=7.4.0; extra == 'dev'
Requires-Dist: ruff>=0.1.0; extra == 'dev'
Provides-Extra: docs
Requires-Dist: mkdocs-material>=9.4.0; extra == 'docs'
Requires-Dist: mkdocs>=1.5.0; extra == 'docs'
Requires-Dist: mkdocstrings[python]>=0.24.0; extra == 'docs'
Provides-Extra: judge
Requires-Dist: anthropic>=0.18.0; extra == 'judge'
Provides-Extra: langchain
Requires-Dist: langchain-community>=0.0.20; extra == 'langchain'
Requires-Dist: langchain-core>=0.1.0; extra == 'langchain'
Requires-Dist: langchain>=0.1.0; extra == 'langchain'
Provides-Extra: viz
Requires-Dist: matplotlib>=3.7.0; extra == 'viz'
Requires-Dist: plotly>=5.15.0; extra == 'viz'
Requires-Dist: seaborn>=0.12.0; extra == 'viz'
